[
  {
    "id":30,
    "source":0,
    "property_preprocess":false,
    "name":"migxFormzUserGroups",
    "description":"",
    "editor_type":0,
    "category":0,
    "cache_type":0,
    "locked":false,
    "properties":[
      
    ],
    "disabled":false,
    "moduleguid":"",
    "static":false,
    "static_file":"",
    "plugin_events":[
      {
        "pluginid":"migxFormzUserGroups",
        "event":"OnFormzFormsBeforeRemove",
        "priority":0,
        "propertyset":0,
        "name":"OnFormzFormsBeforeRemove",
        "service":6,
        "groupname":"FormzExt"
      },
      {
        "pluginid":"migxFormzUserGroups",
        "event":"OnFormzFormsBeforeSave",
        "priority":0,
        "propertyset":0,
        "name":"OnFormzFormsBeforeSave",
        "service":6,
        "groupname":"FormzExt"
      },
      {
        "pluginid":"migxFormzUserGroups",
        "event":"OnFormzFormsCheckPermissions",
        "priority":0,
        "propertyset":0
      },
      {
        "pluginid":"migxFormzUserGroups",
        "event":"OnFormzFormsFieldsBeforeRemove",
        "priority":0,
        "propertyset":0,
        "name":"OnFormzFormsFieldsBeforeRemove",
        "service":6,
        "groupname":"FormzExt"
      },
      {
        "pluginid":"migxFormzUserGroups",
        "event":"OnFormzFormsFieldsBeforeSave",
        "priority":0,
        "propertyset":0,
        "name":"OnFormzFormsFieldsBeforeSave",
        "service":6,
        "groupname":"FormzExt"
      },
      {
        "pluginid":"migxFormzUserGroups",
        "event":"OnFormzFormsPrepareQueryBeforeCount",
        "priority":0,
        "propertyset":0,
        "name":"OnFormzFormsPrepareQueryBeforeCount",
        "service":6,
        "groupname":"FormzExt"
      }
    ],
    "filename":"migxformzusergroups.plugin.php",
    "category_name":"migxFormzUserGroups"
  }
]